haggle/__init__.py
haggle/dacc.py
haggle/small_test.py
haggle-0.1.15.dist-info/LICENSE
haggle-0.1.15.dist-info/METADATA
haggle-0.1.15.dist-info/WHEEL
haggle-0.1.15.dist-info/top_level.txt
haggle-0.1.15.dist-info/RECORD
