Metadata-Version: 2.1
Name: haggle
Version: 0.1.15
Summary: A facade to Kaggle data
Home-page: https://github.com/thorwhalen/haggle
License: mit
Keywords: kaggle,data
Platform: any
License-File: LICENSE
Requires-Dist: kaggle
Requires-Dist: dol
Requires-Dist: py2store
